yotest/__init__.py
yotest/data.pkl
yotest/data_EELS.txt
yotest-0.0.7.dist-info/METADATA
yotest-0.0.7.dist-info/RECORD
yotest-0.0.7.dist-info/WHEEL
yotest-0.0.7.dist-info/top_level.txt
