Metadata-Version: 2.1
Name: yotest
Version: 0.0.7
Summary: Yotest
Home-page: UNKNOWN
Author: Yoman
Author-email: francis.b.lavoie@usherbrooke.ca
License: UNKNOWN
Platform: UNKNOWN
Classifier: Programming Language :: Python :: 3
Classifier: License :: OSI Approved :: MIT License
Classifier: Operating System :: OS Independent
